{"metadata": {"dbt_schema_version": "https://schemas.getdbt.com/dbt/run-results/v4.json", "dbt_version": "1.6.7", "generated_at": "2023-11-07T12:30:15.631528Z", "invocation_id": "1b38ea3d-3adb-4c97-9a1c-c94ee54c74cb", "env": {}}, "results": [{"status": "error", "timing": [{"name": "compile", "started_at": "2023-11-07T12:28:57.729447Z", "completed_at": "2023-11-07T12:28:57.741632Z"}, {"name": "execute", "started_at": "2023-11-07T12:28:57.742149Z", "completed_at": "2023-11-07T12:29:04.630772Z"}], "thread_id": "Thread-1 (worker)", "execution_time": 6.921642780303955, "adapter_response": {}, "message": "Database Error in test dbt_utils_expression_is_true_mrr_date_month_date_trunc_month_current_date_ (models/mrr.yml)\n  Found invalid date part argument function call syntax for `current_date`() at [17:45]\n  compiled Code at target/run/acme/models/mrr.yml/dbt_utils_expression_is_true_m_b3233a8b427f290f3a2e2761afe6d682.sql", "failures": null, "unique_id": "test.acme.dbt_utils_expression_is_true_mrr_date_month_date_trunc_month_current_date_.8e3ee48bc6"}, {"status": "error", "timing": [{"name": "compile", "started_at": "2023-11-07T12:29:04.653693Z", "completed_at": "2023-11-07T12:29:04.660375Z"}, {"name": "execute", "started_at": "2023-11-07T12:29:04.661138Z", "completed_at": "2023-11-07T12:29:11.418053Z"}], "thread_id": "Thread-1 (worker)", "execution_time": 6.772700071334839, "adapter_response": {}, "message": "Database Error in test dbt_utils_expression_is_true_subscription_periods_date_trunc_month_end_date_end_date (models/schema.yml)\n  A valid date part name is required but found end_date at [17:31]\n  compiled Code at target/run/acme/models/schema.yml/dbt_utils_expression_is_true_s_4d81a420147076e873cd54eae2c460ae.sql", "failures": null, "unique_id": "test.acme.dbt_utils_expression_is_true_subscription_periods_date_trunc_month_end_date_end_date.5f773b4670"}, {"status": "error", "timing": [{"name": "compile", "started_at": "2023-11-07T12:29:11.429692Z", "completed_at": "2023-11-07T12:29:11.437940Z"}, {"name": "execute", "started_at": "2023-11-07T12:29:11.438959Z", "completed_at": "2023-11-07T12:29:18.327533Z"}], "thread_id": "Thread-1 (worker)", "execution_time": 6.906739950180054, "adapter_response": {}, "message": "Database Error in test dbt_utils_expression_is_true_subscription_periods_date_trunc_month_start_date_start_date (models/schema.yml)\n  A valid date part name is required but found start_date at [17:31]\n  compiled Code at target/run/acme/models/schema.yml/dbt_utils_expression_is_true_s_55d02e8a711fb54a4345c8b27cf573f2.sql", "failures": null, "unique_id": "test.acme.dbt_utils_expression_is_true_subscription_periods_date_trunc_month_start_date_start_date.abd2cf4dfd"}, {"status": "pass", "timing": [{"name": "compile", "started_at": "2023-11-07T12:29:18.339210Z", "completed_at": "2023-11-07T12:29:18.359012Z"}, {"name": "execute", "started_at": "2023-11-07T12:29:18.359903Z", "completed_at": "2023-11-07T12:29:20.019462Z"}], "thread_id": "Thread-1 (worker)", "execution_time": 1.684880256652832, "adapter_response": {"_message": "SELECT (1.0 rows, 2.8 KiB processed)", "code": "SELECT", "rows_affected": 1, "bytes_processed": 2904, "bytes_billed": 0, "location": "US", "project_id": "production-environment-306717", "job_id": "e3d77915-e444-4b1e-9afa-5f91821c0ab0", "slot_ms": 0}, "message": null, "failures": 0, "unique_id": "test.acme.dbt_utils_mutually_exclusive_ranges_subscription_periods_start_date__customer_id__end_date.a4c8bc64fa"}, {"status": "pass", "timing": [{"name": "compile", "started_at": "2023-11-07T12:29:20.026478Z", "completed_at": "2023-11-07T12:29:20.043963Z"}, {"name": "execute", "started_at": "2023-11-07T12:29:20.044642Z", "completed_at": "2023-11-07T12:29:22.881837Z"}], "thread_id": "Thread-1 (worker)", "execution_time": 2.859076976776123, "adapter_response": {"_message": "SELECT (1.0 rows, 2.8 KiB processed)", "code": "SELECT", "rows_affected": 1, "bytes_processed": 2904, "bytes_billed": 0, "location": "US", "project_id": "production-environment-306717", "job_id": "a73d2f5d-5272-4e18-9336-e68f9604d06d", "slot_ms": 23981}, "message": null, "failures": 0, "unique_id": "test.acme.dbt_utils_unique_combination_of_columns_customer_revenue_by_month_customer_id__date_month.e8886ba716"}, {"status": "pass", "timing": [{"name": "compile", "started_at": "2023-11-07T12:29:22.889915Z", "completed_at": "2023-11-07T12:29:22.900256Z"}, {"name": "execute", "started_at": "2023-11-07T12:29:22.901161Z", "completed_at": "2023-11-07T12:29:26.159676Z"}], "thread_id": "Thread-1 (worker)", "execution_time": 3.273658037185669, "adapter_response": {"_message": "SELECT (1.0 rows, 3.8 KiB processed)", "code": "SELECT", "rows_affected": 1, "bytes_processed": 3872, "bytes_billed": 0, "location": "US", "project_id": "production-environment-306717", "job_id": "1a56e651-ab6d-4ff7-baf4-49ead3a788a1", "slot_ms": 32014}, "message": null, "failures": 0, "unique_id": "test.acme.dbt_utils_unique_combination_of_columns_mrr_customer_id__date_month.7a5b0199cb"}, {"status": "pass", "timing": [{"name": "compile", "started_at": "2023-11-07T12:29:26.167779Z", "completed_at": "2023-11-07T12:29:26.179195Z"}, {"name": "execute", "started_at": "2023-11-07T12:29:26.180176Z", "completed_at": "2023-11-07T12:29:29.197591Z"}], "thread_id": "Thread-1 (worker)", "execution_time": 3.033149003982544, "adapter_response": {"_message": "SELECT (1.0 rows, 3.8 KiB processed)", "code": "SELECT", "rows_affected": 1, "bytes_processed": 3872, "bytes_billed": 0, "location": "US", "project_id": "production-environment-306717", "job_id": "f0aee0f9-6e69-40bc-aec9-c122001a9ec4", "slot_ms": 21323}, "message": null, "failures": 0, "unique_id": "test.acme.not_null_customer_churn_month_customer_id.99e28f508c"}, {"status": "pass", "timing": [{"name": "compile", "started_at": "2023-11-07T12:29:29.210029Z", "completed_at": "2023-11-07T12:29:29.217558Z"}, {"name": "execute", "started_at": "2023-11-07T12:29:29.218510Z", "completed_at": "2023-11-07T12:29:32.292250Z"}], "thread_id": "Thread-1 (worker)", "execution_time": 3.085721731185913, "adapter_response": {"_message": "SELECT (1.0 rows, 3.8 KiB processed)", "code": "SELECT", "rows_affected": 1, "bytes_processed": 3872, "bytes_billed": 0, "location": "US", "project_id": "production-environment-306717", "job_id": "3414136f-8701-4fed-9619-2dd761c20234", "slot_ms": 28081}, "message": null, "failures": 0, "unique_id": "test.acme.not_null_mrr_customer_id.adf44c0fb5"}, {"status": "pass", "timing": [{"name": "compile", "started_at": "2023-11-07T12:29:32.298833Z", "completed_at": "2023-11-07T12:29:32.311337Z"}, {"name": "execute", "started_at": "2023-11-07T12:29:32.312230Z", "completed_at": "2023-11-07T12:29:35.556049Z"}], "thread_id": "Thread-1 (worker)", "execution_time": 3.260101795196533, "adapter_response": {"_message": "SELECT (1.0 rows, 3.8 KiB processed)", "code": "SELECT", "rows_affected": 1, "bytes_processed": 3872, "bytes_billed": 0, "location": "US", "project_id": "production-environment-306717", "job_id": "fef216e7-348a-47bb-903f-996f19ea5d12", "slot_ms": 28601}, "message": null, "failures": 0, "unique_id": "test.acme.not_null_mrr_date_month.d7121d9ce6"}, {"status": "pass", "timing": [{"name": "compile", "started_at": "2023-11-07T12:29:35.562748Z", "completed_at": "2023-11-07T12:29:35.578369Z"}, {"name": "execute", "started_at": "2023-11-07T12:29:35.580685Z", "completed_at": "2023-11-07T12:29:38.536553Z"}], "thread_id": "Thread-1 (worker)", "execution_time": 2.979180097579956, "adapter_response": {"_message": "SELECT (1.0 rows, 3.8 KiB processed)", "code": "SELECT", "rows_affected": 1, "bytes_processed": 3872, "bytes_billed": 0, "location": "US", "project_id": "production-environment-306717", "job_id": "3064de8d-0d73-48d9-8708-c1ad01c682d2", "slot_ms": 30863}, "message": null, "failures": 0, "unique_id": "test.acme.not_null_mrr_first_active_month.a9078832e9"}, {"status": "pass", "timing": [{"name": "compile", "started_at": "2023-11-07T12:29:38.548974Z", "completed_at": "2023-11-07T12:29:38.563392Z"}, {"name": "execute", "started_at": "2023-11-07T12:29:38.564609Z", "completed_at": "2023-11-07T12:29:41.522897Z"}], "thread_id": "Thread-1 (worker)", "execution_time": 2.981091022491455, "adapter_response": {"_message": "SELECT (1.0 rows, 3.8 KiB processed)", "code": "SELECT", "rows_affected": 1, "bytes_processed": 3872, "bytes_billed": 0, "location": "US", "project_id": "production-environment-306717", "job_id": "3976d18d-4b8a-4188-b98c-406af4b81eff", "slot_ms": 27531}, "message": null, "failures": 0, "unique_id": "test.acme.not_null_mrr_id.45914052fb"}, {"status": "pass", "timing": [{"name": "compile", "started_at": "2023-11-07T12:29:41.535372Z", "completed_at": "2023-11-07T12:29:41.550743Z"}, {"name": "execute", "started_at": "2023-11-07T12:29:41.552271Z", "completed_at": "2023-11-07T12:29:44.182241Z"}], "thread_id": "Thread-1 (worker)", "execution_time": 2.651757001876831, "adapter_response": {"_message": "SELECT (1.0 rows, 3.8 KiB processed)", "code": "SELECT", "rows_affected": 1, "bytes_processed": 3872, "bytes_billed": 0, "location": "US", "project_id": "production-environment-306717", "job_id": "094b8b22-f0d2-43ae-802e-66b729488aa0", "slot_ms": 13868}, "message": null, "failures": 0, "unique_id": "test.acme.not_null_mrr_is_active.66e2203f7d"}, {"status": "pass", "timing": [{"name": "compile", "started_at": "2023-11-07T12:29:44.192516Z", "completed_at": "2023-11-07T12:29:44.213206Z"}, {"name": "execute", "started_at": "2023-11-07T12:29:44.214324Z", "completed_at": "2023-11-07T12:29:49.105863Z"}], "thread_id": "Thread-1 (worker)", "execution_time": 4.91998291015625, "adapter_response": {"_message": "SELECT (1.0 rows, 3.8 KiB processed)", "code": "SELECT", "rows_affected": 1, "bytes_processed": 3872, "bytes_billed": 0, "location": "US", "project_id": "production-environment-306717", "job_id": "c3b8d947-2d46-47f7-b47e-b2df44e0ad44", "slot_ms": 13846}, "message": null, "failures": 0, "unique_id": "test.acme.not_null_mrr_is_first_month.97ecc2049e"}, {"status": "pass", "timing": [{"name": "compile", "started_at": "2023-11-07T12:29:49.119363Z", "completed_at": "2023-11-07T12:29:49.134224Z"}, {"name": "execute", "started_at": "2023-11-07T12:29:49.135884Z", "completed_at": "2023-11-07T12:29:51.982945Z"}], "thread_id": "Thread-1 (worker)", "execution_time": 2.869844913482666, "adapter_response": {"_message": "SELECT (1.0 rows, 3.8 KiB processed)", "code": "SELECT", "rows_affected": 1, "bytes_processed": 3872, "bytes_billed": 0, "location": "US", "project_id": "production-environment-306717", "job_id": "4477fa1e-f0ec-46d5-9d41-58dd6c629fc8", "slot_ms": 12414}, "message": null, "failures": 0, "unique_id": "test.acme.not_null_mrr_is_last_month.a91990c0de"}, {"status": "pass", "timing": [{"name": "compile", "started_at": "2023-11-07T12:29:51.993368Z", "completed_at": "2023-11-07T12:29:52.007443Z"}, {"name": "execute", "started_at": "2023-11-07T12:29:52.008563Z", "completed_at": "2023-11-07T12:29:55.183298Z"}], "thread_id": "Thread-1 (worker)", "execution_time": 3.196653127670288, "adapter_response": {"_message": "SELECT (1.0 rows, 3.8 KiB processed)", "code": "SELECT", "rows_affected": 1, "bytes_processed": 3872, "bytes_billed": 0, "location": "US", "project_id": "production-environment-306717", "job_id": "1185a32c-6a31-4092-b417-821015bea0a4", "slot_ms": 24786}, "message": null, "failures": 0, "unique_id": "test.acme.not_null_mrr_last_active_month.c5f2565121"}, {"status": "pass", "timing": [{"name": "compile", "started_at": "2023-11-07T12:29:55.194850Z", "completed_at": "2023-11-07T12:29:55.203575Z"}, {"name": "execute", "started_at": "2023-11-07T12:29:55.204649Z", "completed_at": "2023-11-07T12:29:56.849682Z"}], "thread_id": "Thread-1 (worker)", "execution_time": 1.660489797592163, "adapter_response": {"_message": "SELECT (1.0 rows, 0 processed)", "code": "SELECT", "rows_affected": 1, "bytes_processed": 0, "bytes_billed": 0, "location": "US", "project_id": "production-environment-306717", "job_id": "28e43417-421d-44ec-be04-1d8f987640b2", "slot_ms": 5}, "message": null, "failures": 0, "unique_id": "test.acme.not_null_mrr_mrr.7e419847d2"}, {"status": "pass", "timing": [{"name": "compile", "started_at": "2023-11-07T12:29:56.862285Z", "completed_at": "2023-11-07T12:29:56.883103Z"}, {"name": "execute", "started_at": "2023-11-07T12:29:56.884539Z", "completed_at": "2023-11-07T12:30:00.696143Z"}], "thread_id": "Thread-1 (worker)", "execution_time": 3.8410558700561523, "adapter_response": {"_message": "SELECT (1.0 rows, 3.8 KiB processed)", "code": "SELECT", "rows_affected": 1, "bytes_processed": 3872, "bytes_billed": 0, "location": "US", "project_id": "production-environment-306717", "job_id": "d017ddcd-6568-49d0-8e80-5c12e527a37d", "slot_ms": 28092}, "message": null, "failures": 0, "unique_id": "test.acme.not_null_mrr_mrr_change.0329647bd8"}, {"status": "pass", "timing": [{"name": "compile", "started_at": "2023-11-07T12:30:00.708876Z", "completed_at": "2023-11-07T12:30:00.720955Z"}, {"name": "execute", "started_at": "2023-11-07T12:30:00.722153Z", "completed_at": "2023-11-07T12:30:04.255110Z"}], "thread_id": "Thread-1 (worker)", "execution_time": 3.553276300430298, "adapter_response": {"_message": "SELECT (1.0 rows, 3.8 KiB processed)", "code": "SELECT", "rows_affected": 1, "bytes_processed": 3872, "bytes_billed": 0, "location": "US", "project_id": "production-environment-306717", "job_id": "c801d9fb-bc67-454b-a859-de18925a2828", "slot_ms": 26230}, "message": null, "failures": 0, "unique_id": "test.acme.not_null_mrr_previous_month_is_active.836f1724d2"}, {"status": "pass", "timing": [{"name": "compile", "started_at": "2023-11-07T12:30:04.269256Z", "completed_at": "2023-11-07T12:30:04.282525Z"}, {"name": "execute", "started_at": "2023-11-07T12:30:04.283740Z", "completed_at": "2023-11-07T12:30:08.248626Z"}], "thread_id": "Thread-1 (worker)", "execution_time": 3.985630989074707, "adapter_response": {"_message": "SELECT (1.0 rows, 3.8 KiB processed)", "code": "SELECT", "rows_affected": 1, "bytes_processed": 3872, "bytes_billed": 0, "location": "US", "project_id": "production-environment-306717", "job_id": "822b0431-e069-41ce-b4b9-40a471f8fcf9", "slot_ms": 25633}, "message": null, "failures": 0, "unique_id": "test.acme.not_null_mrr_previous_month_mrr.9a7dfac4d7"}, {"status": "pass", "timing": [{"name": "compile", "started_at": "2023-11-07T12:30:08.260890Z", "completed_at": "2023-11-07T12:30:08.276581Z"}, {"name": "execute", "started_at": "2023-11-07T12:30:08.278251Z", "completed_at": "2023-11-07T12:30:11.636831Z"}], "thread_id": "Thread-1 (worker)", "execution_time": 3.382266044616699, "adapter_response": {"_message": "SELECT (1.0 rows, 3.8 KiB processed)", "code": "SELECT", "rows_affected": 1, "bytes_processed": 3872, "bytes_billed": 0, "location": "US", "project_id": "production-environment-306717", "job_id": "3cffe693-605b-452f-8014-4899c8aaeb12", "slot_ms": 19949}, "message": null, "failures": 0, "unique_id": "test.acme.unique_customer_churn_month_customer_id.a402b7af3f"}, {"status": "pass", "timing": [{"name": "compile", "started_at": "2023-11-07T12:30:11.648879Z", "completed_at": "2023-11-07T12:30:11.661321Z"}, {"name": "execute", "started_at": "2023-11-07T12:30:11.662821Z", "completed_at": "2023-11-07T12:30:15.615828Z"}], "thread_id": "Thread-1 (worker)", "execution_time": 3.973478078842163, "adapter_response": {"_message": "SELECT (1.0 rows, 3.8 KiB processed)", "code": "SELECT", "rows_affected": 1, "bytes_processed": 3872, "bytes_billed": 0, "location": "US", "project_id": "production-environment-306717", "job_id": "629f7a03-56d0-47c9-880b-4070adb5e6fa", "slot_ms": 14853}, "message": null, "failures": 0, "unique_id": "test.acme.unique_mrr_id.a14d6c26bd"}], "elapsed_time": 79.14683175086975, "args": {"profiles_dir": "/Users/olaisaac/.dbt", "introspect": true, "populate_cache": true, "project_dir": "/Users/olaisaac/projects/dbt-test-playbook", "use_colors_file": true, "partial_parse_file_diff": true, "use_colors": true, "invocation_command": "dbt test", "log_format": "default", "log_format_file": "debug", "quiet": false, "defer": false, "log_level": "info", "send_anonymous_usage_stats": true, "enable_legacy_logger": false, "warn_error_options": {"include": [], "exclude": []}, "write_json": true, "favor_state": false, "macro_debugging": false, "static_parser": true, "print": true, "version_check": true, "log_file_max_bytes": 10485760, "vars": {}, "log_level_file": "debug", "printer_width": 80, "cache_selected_only": false, "exclude": [], "indirect_selection": "eager", "log_path": "/Users/olaisaac/projects/dbt-test-playbook/logs", "which": "test", "select": [], "strict_mode": false, "partial_parse": true}}